check_uncommitted_git_changes/__init__.py
check_uncommitted_git_changes/main.py
check_uncommitted_git_changes-1.0.1.dist-info/entry_points.txt
check_uncommitted_git_changes-1.0.1.dist-info/LICENSE.txt
check_uncommitted_git_changes-1.0.1.dist-info/WHEEL
check_uncommitted_git_changes-1.0.1.dist-info/METADATA
check_uncommitted_git_changes-1.0.1.dist-info/RECORD
