Metadata-Version: 2.1
Name: check-uncommitted-git-changes
Version: 1.0.1
Summary: check for uncommitted git changes to identify outdated generated content during continuous integration
Home-page: https://github.com/roskakori/check_uncommitted_git_changes
License: BSD
Keywords: check,ci,git
Author: Thomas Aglassinger
Author-email: roskakori@users.sourceforge.net
Requires-Python: >=3.7,<4.0
Classifier: Development Status :: 5 - Production/Stable
Classifier: Environment :: Console
Classifier: Intended Audience :: Developers
Classifier: License :: OSI Approved :: BSD License
Classifier: License :: Other/Proprietary License
Classifier: Natural Language :: English
Classifier: Operating System :: OS Independent
Classifier: Programming Language :: Python :: 3
Classifier: Programming Language :: Python :: 3 :: Only
Classifier: Programming Language :: Python :: 3.10
Classifier: Programming Language :: Python :: 3.7
Classifier: Programming Language :: Python :: 3.8
Classifier: Programming Language :: Python :: 3.9
Classifier: Topic :: Software Development
Classifier: Topic :: Software Development :: Code Generators
Classifier: Topic :: Software Development :: Quality Assurance
Classifier: Topic :: Software Development :: Version Control :: Git
Project-URL: Changes, https://github.com/roskakori/check_uncommitted_git_changes/blob/main/CHANGES.md
Project-URL: Issue Tracker, https://github.com/roskakori/check_uncommitted_git_changes/issues
Project-URL: Repository, https://github.com/roskakori/check_uncommitted_git_changes.git
